dot4dict/__init__.py
dot4dict-0.1.1.dist-info/LICENSE
dot4dict-0.1.1.dist-info/METADATA
dot4dict-0.1.1.dist-info/WHEEL
dot4dict-0.1.1.dist-info/top_level.txt
dot4dict-0.1.1.dist-info/RECORD
