Metadata-Version: 2.1
Name: dot4dict
Version: 0.1.1
Summary: A Python Package to enable dot-notation on dictionaries
Home-page: https://github.com/zincware/dot4dict
Download-URL: https://github.com/zincware/dot4dict/archive/beta.tar.gz
Author: zincwarecode
Author-email: zincwarecode@gmail.com
License: UNKNOWN
Keywords: dotdict,dict2dot
Platform: UNKNOWN
Classifier: Development Status :: 4 - Beta
Classifier: Programming Language :: Python :: 3
Classifier: License :: OSI Approved :: Apache Software License
Classifier: Operating System :: OS Independent
Requires-Python: >=3.7
License-File: LICENSE
